README.rst
setup.py
hyperschema/__init__.py
hyperschema/data.py
hyperschema/link.py
hyperschema/schema.py
hyperschema.egg-info/PKG-INFO
hyperschema.egg-info/SOURCES.txt
hyperschema.egg-info/dependency_links.txt
hyperschema.egg-info/requires.txt
hyperschema.egg-info/top_level.txt
tests/__init__.py
tests/test_data.py
tests/test_link.py
tests/test_schema.py