Metadata-Version: 1.1
Name: hyperschema
Version: 0.2.1
Summary: Python client library for JSON hyperschema REST services
Home-page: https://github.com/wuan/python-hyperschema
Author: Andreas Würl
Author-email: andreas@wuerl.net
License: Apache-2.0
Platform: UNKNOWN
Classifier: Development Status :: 3 - Alpha
Classifier: Intended Audience :: Developers
Classifier: Topic :: Internet :: WWW/HTTP :: Dynamic Content
Classifier: License :: OSI Approved :: Apache Software License
Classifier: Programming Language :: Python :: 3
Classifier: Programming Language :: Python :: 3.2
Classifier: Programming Language :: Python :: 3.3
Classifier: Programming Language :: Python :: 3.4
